LICENSE.txt
MANIFEST.in
README.md
setup.cfg
setup.py
./LICENSE.txt
./README.md
./setup.py
./Misc/ApyPSFPhot.py
./Misc/ApyPhot.py
./Misc/DaoPhot.py
./Misc/GetFWHM.py
./Misc/GetPicsA.py
./SRPGW/ApyPSFPhot.py
./SRPGW/ApyPhot.py
./SRPGW/CheckMagDiff.py
./SRPGW/Chi2.py
./SRPGW/DaoPSFPhot.py
./SRPGW/DaoPhot.py
./SRPGW/FindPathes.py
./SRPGW/FindSubPathes.py
./SRPGW/Flux2Mag.py
./SRPGW/GetApPhot.py
./SRPGW/GetCommandStr.py
./SRPGW/GetFits.py
./SRPGW/GetGAIAxMatch.py
./SRPGW/GetGLADExMatch.py
./SRPGW/GetHeadVal.py
./SRPGW/GetIGAIA.py
./SRPGW/GetIGAIAxMatch.py
./SRPGW/GetLEDAxMatch.py
./SRPGW/GetNEDMatch .py
./SRPGW/GetPSFPhot.py
./SRPGW/GetPanSTARRS.py
./SRPGW/GetPics.py
./SRPGW/GetPixVal.py
./SRPGW/GetPixXY.py
./SRPGW/GetSDSSxMatch.py
./SRPGW/GetSimbad.py
./SRPGW/GetSimbadxMatch.py
./SRPGW/GetSkyBot.py
./SRPGW/GetSkyBotMatch.py
./SRPGW/GetTest.py
./SRPGW/GetUSNOxMatch.py
./SRPGW/GetWeights.py
./SRPGW/IsCoordIn.py
./SRPGW/MyPhot.py
./SRPGW/ReadDate.py
./SRPGW/Score.py
./SRPGW/SexPhot.py
./SRPGW/__init__.py
./build/lib/SRPGW/ApyPSFPhot.py
./build/lib/SRPGW/ApyPhot.py
./build/lib/SRPGW/CheckMagDiff.py
./build/lib/SRPGW/Chi2.py
./build/lib/SRPGW/DaoPSFPhot.py
./build/lib/SRPGW/DaoPhot.py
./build/lib/SRPGW/FindPathes.py
./build/lib/SRPGW/FindSubPathes.py
./build/lib/SRPGW/Flux2Mag.py
./build/lib/SRPGW/GetApPhot.py
./build/lib/SRPGW/GetCommandStr.py
./build/lib/SRPGW/GetFits.py
./build/lib/SRPGW/GetGAIAxMatch.py
./build/lib/SRPGW/GetGLADExMatch.py
./build/lib/SRPGW/GetHeadVal.py
./build/lib/SRPGW/GetIGAIA.py
./build/lib/SRPGW/GetIGAIAxMatch.py
./build/lib/SRPGW/GetLEDAxMatch.py
./build/lib/SRPGW/GetNEDMatch .py
./build/lib/SRPGW/GetPSFPhot.py
./build/lib/SRPGW/GetPanSTARRS.py
./build/lib/SRPGW/GetPics.py
./build/lib/SRPGW/GetPixVal.py
./build/lib/SRPGW/GetPixXY.py
./build/lib/SRPGW/GetSDSSxMatch.py
./build/lib/SRPGW/GetSimbad.py
./build/lib/SRPGW/GetSimbadxMatch.py
./build/lib/SRPGW/GetSkyBot.py
./build/lib/SRPGW/GetSkyBotMatch.py
./build/lib/SRPGW/GetTest.py
SRPAstro.GW.egg-info/PKG-INFO
SRPAstro.GW.egg-info/SOURCES.txt
SRPAstro.GW.egg-info/dependency_links.txt
SRPAstro.GW.egg-info/requires.txt
SRPAstro.GW.egg-info/top_level.txt
